termtable/__init__.py
termtable/colour_helpers.py
termtable/utils.py
termtable-1.0.0.dist-info/METADATA
termtable-1.0.0.dist-info/RECORD
termtable-1.0.0.dist-info/WHEEL
termtable-1.0.0.dist-info/top_level.txt
